degit/EthereumClient.py
degit/__init__.py
degit/degit.py
degit/demo.py
degit/main.py
degit/utils.py
degit/compiled_contracts/repository_abi.json
degit/compiled_contracts/repository_bytecode.txt
degit-0.0.1.dist-info/LICENSE
degit-0.0.1.dist-info/METADATA
degit-0.0.1.dist-info/WHEEL
degit-0.0.1.dist-info/entry_points.txt
degit-0.0.1.dist-info/top_level.txt
degit-0.0.1.dist-info/RECORD
