Metadata-Version: 2.1
Name: degit
Version: 0.0.1
Summary: de-centrailized git
Home-page: https://github.com/lchalex/MSBD5017_project
Author: Royinx, Thomas, Alex
Author-email: 
License: UNKNOWN
Project-URL: Bug Tracker, https://github.com/lchalex/MSBD5017_project/issues
Platform: UNKNOWN
Classifier: Programming Language :: Python :: 3
Classifier: License :: OSI Approved :: MIT License
Classifier: Operating System :: OS Independent
Requires-Python: >=3.8
License-File: LICENSE
